Metadata-Version: 2.1
Name: tfnumpy
Version: 0.0.6
Summary: Collection of Simple Numerical Routines using TensorFlow
Home-page: https://github.com/stephenhky/TFNumPy
Author: Kwan-Yuet Ho
Author-email: stephenhky@yahoo.com.hk
License: MIT
Keywords: numerics computation tensorflow
Platform: UNKNOWN
Classifier: Topic :: Scientific/Engineering :: Mathematics
Classifier: Programming Language :: Python :: 2.7
Classifier: Programming Language :: Python :: 3.5
Classifier: Programming Language :: Python :: 3.6
Classifier: Programming Language :: Python :: 3.7
Classifier: License :: OSI Approved :: MIT License
